didppy-0.10.0.dist-info/METADATA
didppy-0.10.0.dist-info/WHEEL
didppy/__init__.py
didppy/didppy.pyd
didppy-0.10.0.dist-info/RECORD
