Metadata-Version: 2.4
Name: didppy
Version: 0.10.0
Classifier: Programming Language :: Rust
Classifier: Programming Language :: Python :: Implementation :: CPython
Classifier: Programming Language :: Python :: Implementation :: PyPy
Requires-Dist: pytest ; extra == 'dev'
Requires-Dist: flake8 ; extra == 'dev'
Requires-Dist: black ; extra == 'dev'
Requires-Dist: isort ; extra == 'dev'
Provides-Extra: dev
Home-Page: https://didp.ai
Author-email: Ryo Kuroiwa <kuroiwa@nii.ac.jp>, "Yuxiao (Jasper) Chen" <yuxiao.chen@mail.utoronto.ca>, Anubhav Singh <anubhav.singh@utoronto.ca>
Requires-Python: >=3.7
